Lab4/q4.v
module halfAdder(a,b,carry,sum);
	input a,b;
	output sum,carry;
	assign sum = a^b;
	assign carry = a&b;
endmodule

module q4(a0,a1,b0,b1,p0,p1,p2,p3);
	input a0,a1,b0,b1;
	output p3,p2,p1,p0;

	
	assign p0 = a0 & b0 ;
	halfAdder ha1(a0 & b1, a1 & b0, c1, p1);
	halfAdder ha2(p0, c1, c2, p2);
	halfAdder ha3(a1 & b1, p1, p3, s3);

endmodule

Lab4/q4_tb.v
`timescale 1ns/1ns
`include "q4.v" 

module ex();

    reg a0, a1, b0, b1;

    wire p3, p2, p1, p0;

    q4 ex1(a0, a1, b0, b1, p3, p2, p1, p0);

    initial begin

        $dumpfile("q4_tb.vcd");
        $dumpvars(0, ex1); 


        a0 = 0; a1 = 0; b0 = 0; b1 = 0; #20;
        a0 = 0; a1 = 0; b0 = 0; b1 = 1; #20;
        a0 = 0; a1 = 0; b0 = 1; b1 = 0; #20;
        a0 = 0; a1 = 0; b0 = 1; b1 = 1; #20;
        a0 = 0; a1 = 1; b0 = 0; b1 = 0; #20;
        a0 = 0; a1 = 1; b0 = 0; b1 = 1; #20;
        a0 = 0; a1 = 1; b0 = 1; b1 = 0; #20;
        a0 = 0; a1 = 1; b0 = 1; b1 = 1; #20;
        a0 = 1; a1 = 0; b0 = 0; b1 = 0; #20;
        a0 = 1; a1 = 0; b0 = 0; b1 = 1; #20;
        a0 = 1; a1 = 0; b0 = 1; b1 = 0; #20;
        a0 = 1; a1 = 0; b0 = 1; b1 = 1; #20;
        a0 = 1; a1 = 1; b0 = 0; b1 = 0; #20;
        a0 = 1; a1 = 1; b0 = 0; b1 = 1; #20;
        a0 = 1; a1 = 1; b0 = 1; b1 = 0; #20;
        a0 = 1; a1 = 1; b0 = 1; b1 = 1; #20;


        $display("Test complete");
        end
endmodule

Lab4/q4_tb.vcd
$date
	Mon Aug 18 10:15:48 2025
$end
$version
	Icarus Verilog
$end
$timescale
	1ns
$end
$scope module ex $end
$scope module ex1 $end
$var wire 1 ! a0 $end
$var wire 1 " a1 $end
$var wire 1 # b0 $end
$var wire 1 $ b1 $end
$var wire 1 % p0 $end
$var wire 1 & s3 $end
$var wire 1 ' p3 $end
$var wire 1 ( p2 $end
$var wire 1 ) p1 $end
$var wire 1 * c2 $end
$var wire 1 + c1 $end
$scope module ha1 $end
$var wire 1 , a $end
$var wire 1 - b $end
$var wire 1 + carry $end
$var wire 1 ) sum $end
$upscope $end
$scope module ha2 $end
$var wire 1 % a $end
$var wire 1 + b $end
$var wire 1 * carry $end
$var wire 1 ( sum $end
$upscope $end
$scope module ha3 $end
$var wire 1 . a $end
$var wire 1 ) b $end
$var wire 1 ' carry $end
$var wire 1 & sum $end
$upscope $end
$upscope $end
$upscope $end
$enddefinitions $end
#0
$dumpvars
0.
0-
0,
0+
0*
0)
0(
0'
0&
0%
0$
0#
0"
0!
$end
#20
1$
#40
0$
1#
#60
1$
#80
0$
0#
1"
#100
1&
1.
1$
#120
1)
0.
1-
0$
1#
#140
0&
1'
1.
1$
#160
0)
0&
0'
0-
0.
0$
0#
0"
1!
#180
1&
1)
1,
1$
#200
0&
0)
1(
0,
1%
0$
1#
#220
1&
1)
1,
1$
#240
0&
0)
0(
0,
0%
0$
0#
1"
#260
1'
1)
0&
1,
1.
1$
#280
1&
0'
1(
0,
0.
1%
1-
0$
1#
#300
0(
1*
0)
1+
1&
0'
1,
1.
1$
