Lab2/q2_1.v
module q2_1(a,b,c,d,f);
input a,b,c,d;
output f;
assign f = (b | ~c) & (~b | ~d);
endmodule

Lab2/q2_1_tb.v
`timescale 1ns / 1ns
`include "q2_1.v"

module ex();
    reg a, b, c, d;
    wire f;
    q2_1 example(a, b, c, d, f);
    
    // Test sequence
    initial begin
        $dumpfile("q2_1.vcd");
        $dumpvars(0, ex);
        
        a = 1'b0; b = 1'b0; c = 1'b0; d = 1'b0; #20;
        a = 1'b0; b = 1'b0; c = 1'b0; d = 1'b1; #20;
        a = 1'b0; b = 1'b0; c = 1'b1; d = 1'b0; #20;
        a = 1'b0; b = 1'b0; c = 1'b1; d = 1'b1; #20;
        a = 1'b0; b = 1'b1; c = 1'b0; d = 1'b0; #20;
        a = 1'b0; b = 1'b1; c = 1'b0; d = 1'b1; #20;
        a = 1'b0; b = 1'b1; c = 1'b1; d = 1'b0; #20;
        a = 1'b0; b = 1'b1; c = 1'b1; d = 1'b1; #20;
        a = 1'b1; b = 1'b0; c = 1'b0; d = 1'b0; #20;
        a = 1'b1; b = 1'b0; c = 1'b0; d = 1'b1; #20;
        a = 1'b1; b = 1'b0; c = 1'b1; d = 1'b0; #20;
        a = 1'b1; b = 1'b0; c = 1'b1; d = 1'b1; #20;
        a = 1'b1; b = 1'b1; c = 1'b0; d = 1'b0; #20;
        a = 1'b1; b = 1'b1; c = 1'b0; d = 1'b1; #20;
        a = 1'b1; b = 1'b1; c = 1'b1; d = 1'b0; #20;
        a = 1'b1; b = 1'b1; c = 1'b1; d = 1'b1; #20;
        
        $display("Test complete");
    end
endmodule

Lab2/q2_2.vcd
$date
	Mon Aug  4 08:57:20 2025
$end
$version
	Icarus Verilog
$end
$timescale
	1ns
$end
$scope module ex $end
$var wire 1 ! f $end
$var reg 1 " a $end
$var reg 1 # b $end
$var reg 1 $ c $end
$var reg 1 % d $end
$scope module example $end
$var wire 1 " a $end
$var wire 1 # b $end
$var wire 1 $ c $end
$var wire 1 % d $end
$var wire 1 ! f $end
$upscope $end
$upscope $end
$enddefinitions $end
#0
$dumpvars
0%
0$
0#
0"
0!
$end
#20
1%
#40
1!
0%
1$
#60
0!
1%
#80
1!
0%
0$
1#
#100
0!
1%
#120
1!
0%
1$
#140
0!
1%
#160
0!
0%
0$
0#
1"
#180
1!
1%
#200
0%
1$
#220
1%
#240
0%
0$
1#
#260
1%
#280
0!
0%
1$
#300
1%
