Lab3/q1.v
module q1(a,b,c,d,f,g);
input a,b,c,d;
output f,g;
assign g = (~a|b)&(~c|d);
nand(x1,b,b);
nand(x2,d,d);
nand(x3,x1,a);
nand(x4,x2,c);
nand(x5,x3,x4);
nand(f,x5,x5);
endmodule

Lab3/q1_tb.v
`timescale 1ns / 1ns
`include "q1.v"

module ex();
    reg a, b, c, d;
    wire f,g;
    q1 example(a, b, c, d, f, g);
    
    // Test sequence
    initial begin
        $dumpfile("q1.vcd");
        $dumpvars(0, ex);
        
        a = 1'b0; b = 1'b0; c = 1'b0; d = 1'b0; #20;
        a = 1'b0; b = 1'b0; c = 1'b0; d = 1'b1; #20;
        a = 1'b0; b = 1'b0; c = 1'b1; d = 1'b0; #20;
        a = 1'b0; b = 1'b0; c = 1'b1; d = 1'b1; #20;
        a = 1'b0; b = 1'b1; c = 1'b0; d = 1'b0; #20;
        a = 1'b0; b = 1'b1; c = 1'b0; d = 1'b1; #20;
        a = 1'b0; b = 1'b1; c = 1'b1; d = 1'b0; #20;
        a = 1'b0; b = 1'b1; c = 1'b1; d = 1'b1; #20;
        a = 1'b1; b = 1'b0; c = 1'b0; d = 1'b0; #20;
        a = 1'b1; b = 1'b0; c = 1'b0; d = 1'b1; #20;
        a = 1'b1; b = 1'b0; c = 1'b1; d = 1'b0; #20;
        a = 1'b1; b = 1'b0; c = 1'b1; d = 1'b1; #20;
        a = 1'b1; b = 1'b1; c = 1'b0; d = 1'b0; #20;
        a = 1'b1; b = 1'b1; c = 1'b0; d = 1'b1; #20;
        a = 1'b1; b = 1'b1; c = 1'b1; d = 1'b0; #20;
        a = 1'b1; b = 1'b1; c = 1'b1; d = 1'b1; #20;
        
        $display("Test complete");
    end
endmodule

Lab3/q1.vcd
$date
	Mon Aug 11 08:14:44 2025
$end
$version
	Icarus Verilog
$end
$timescale
	1ns
$end
$scope module ex $end
$var wire 1 ! g $end
$var wire 1 " f $end
$var reg 1 # a $end
$var reg 1 $ b $end
$var reg 1 % c $end
$var reg 1 & d $end
$scope module example $end
$var wire 1 # a $end
$var wire 1 $ b $end
$var wire 1 % c $end
$var wire 1 & d $end
$var wire 1 " f $end
$var wire 1 ! g $end
$var wire 1 ' x1 $end
$var wire 1 ( x2 $end
$var wire 1 ) x3 $end
$var wire 1 * x4 $end
$var wire 1 + x5 $end
$upscope $end
$upscope $end
$enddefinitions $end
#0
$dumpvars
0+
1*
1)
1(
1'
0&
0%
0$
0#
1"
1!
$end
#20
0(
1&
#40
0"
1+
0!
0*
1(
0&
1%
#60
1"
0+
1!
1*
0(
1&
#80
1(
0'
0&
0%
1$
#100
0(
1&
#120
0"
1+
0!
0*
1(
0&
1%
#140
1"
0+
1!
1*
0(
1&
#160
0"
1+
0!
0)
1(
1'
0&
0%
0$
1#
#180
0(
1&
#200
0*
1(
0&
1%
#220
1*
0(
1&
#240
1"
0+
1!
1)
1(
0'
0&
0%
1$
#260
0(
1&
#280
0"
1+
0!
0*
1(
0&
1%
#300
1"
0+
1!
1*
0(
1&
